raymon/__init__.py
raymon/api.py
raymon/exceptions.py
raymon/globals.py
raymon/loggers.py
raymon/out.py
raymon/tags.py
raymon/trace.py
raymon/types.py
raymon/version.py
raymon/auth/__init__.py
raymon/auth/m2m.py
raymon/auth/user.py
raymon/frontend/raymon.min.js
raymon/frontend/raymon.min.js.map
raymon/models/mobilenetv2-7.onnx
raymon/profiling/__init__.py
raymon/profiling/components.py
raymon/profiling/profiles.py
raymon/profiling/scores.py
raymon/profiling/stats.py
raymon/profiling/utils.py
raymon/profiling/extractors/__init__.py
raymon/profiling/extractors/extractors.py
raymon/profiling/extractors/structured/__init__.py
raymon/profiling/extractors/structured/element.py
raymon/profiling/extractors/structured/entropy.py
raymon/profiling/extractors/structured/iforest.py
raymon/profiling/extractors/structured/kmeans.py
raymon/profiling/extractors/structured/margin.py
raymon/profiling/extractors/structured/scoring.py
raymon/profiling/extractors/vision/__init__.py
raymon/profiling/extractors/vision/anomaly.py
raymon/profiling/extractors/vision/intensity.py
raymon/profiling/extractors/vision/sharpness.py
raymon/profiling/extractors/vision/similarity.py
raymon/profiling/extractors/vision/yolo.py
raymon-0.0.39.dist-info/LICENSE.md
raymon-0.0.39.dist-info/METADATA
raymon-0.0.39.dist-info/WHEEL
raymon-0.0.39.dist-info/top_level.txt
raymon-0.0.39.dist-info/RECORD
