Metadata-Version: 2.1
Name: raymon
Version: 0.0.39
Summary: Python package for data logging and monitoring.
Home-page: https://raymon.ai
Author: Raymon.ai
Author-email: hello@raymon.ai
License: MIT
Platform: UNKNOWN
Classifier: Programming Language :: Python :: 3
Requires-Python: >=3.6
Requires-Dist: pyyaml
Requires-Dist: msgpack (==1.0.0)
Requires-Dist: pendulum
Requires-Dist: click
Requires-Dist: pandas
Requires-Dist: requests
Requires-Dist: Pillow
Requires-Dist: onnxruntime (==1.8.0)
Requires-Dist: imagehash
Requires-Dist: sklearn
